opentelemetry/instrumentation/digma/__init__.py
opentelemetry/instrumentation/digma/digma_configuration.py
opentelemetry/instrumentation/digma/instrumentation_extensions.py
opentelemetry/instrumentation/digma/opentelemetry_utils.py
opentelemetry/instrumentation/digma/resource_attributes.py
opentelemetry/instrumentation/digma/trace_decorator.py
opentelemetry/instrumentation/digma/version.py
opentelemetry_instrumentation_digma-0.9.0.dist-info/LICENSE
opentelemetry_instrumentation_digma-0.9.0.dist-info/METADATA
opentelemetry_instrumentation_digma-0.9.0.dist-info/WHEEL
opentelemetry_instrumentation_digma-0.9.0.dist-info/top_level.txt
opentelemetry_instrumentation_digma-0.9.0.dist-info/RECORD
